xurls/__init__.py
xurls/url.py
xurls-1.4.1.dist-info/LICENSE
xurls-1.4.1.dist-info/METADATA
xurls-1.4.1.dist-info/WHEEL
xurls-1.4.1.dist-info/RECORD
