Metadata-Version: 2.3
Name: xurls
Version: 1.4.1
Summary: Python URL Library
Author: Josh Orr
Author-email: josh@orr.blue
Requires-Python: >=3.10,<4.0
Classifier: License :: OSI Approved :: The Unlicense (Unlicense)
Classifier: Programming Language :: Python :: 3
Classifier: Programming Language :: Python :: 3.10
Classifier: Programming Language :: Python :: 3.11
Classifier: Programming Language :: Python :: 3.12
Classifier: Programming Language :: Python :: 3.13
Classifier: Topic :: Software Development :: Libraries :: Python Modules
Requires-Dist: xloop (>=1.0.1,<2.0.0)
Requires-Dist: xsentinels (>=1.2.1,<2.0.0)
Project-URL: Repository, https://github.com/joshorr/xurls
